better_zipfile
