Metadata-Version: 2.1
Name: better-zipfile
Version: 0.0.3
Summary: 本项目旨在对优化python中自带的zipfile，以处理mnbvc项目解压遇到的问题
Home-page: https://github.com/aplmikex/better_zipfile
Author: aplmikex
Author-email: 2738186032@qq.com
Project-URL: Bug Reports, https://github.com/aplmikex/better_zipfile/issues
Project-URL: Source, https://github.com/aplmikex/better_zipfile/
Classifier: License :: OSI Approved :: MIT License
Classifier: Programming Language :: Python :: 3
Requires-Python: >=3.7
License-File: LICENSE
